rtl/clock_divider.sv
module clock_divider #(
    parameter DIVISOR
) (
    input logic clk_in,
    input logic resetn,
    output logic clk_out
);
    int counter = 0;
    always_ff @(posedge clk_in) begin
        if (!resetn) begin
            clk_out <= 1'b0;
            counter <= 0;
        end else begin
            counter <= counter + 1;
            if (counter == DIVISOR - 1) begin
                clk_out <= ~clk_out;
                counter <= 0;
            end
        end
    end 
endmodule

tb/clock_divider_tb.sv
`timescale 1ns/1ps
module clock_divider_tb;
    logic clk_in;
    logic resetn;
    logic clk_out;

    localparam DIVISOR = 4;

    clock_divider #(.DIVISOR(DIVISOR)) dut (
        .clk_in(clk_in),
        .resetn(resetn),
        .clk_out(clk_out)
    );

    //HOW TO GENERATE CLOCK
    initial clk_in = 0;
    always begin
        #5 clk_in = ~clk_in;
    end

    initial begin
        $dumpfile("sim/clock_divider_tb.vcd");
        $dumpvars(0, clock_divider_tb);

        clk_in = 1'b0;
        resetn = 1'b0;
        #10 resetn = 1'b1; // Release reset after 10 time units
        #500;
        $display("Simulation finished %t", $time);
        $finish; // Finish simulation after 500 time units
    end  
    
endmodule

sim/clock_divider_tb.vcd
$date
	Tue Jun 30 11:38:17 2026
$end
$version
	Icarus Verilog
$end
$timescale
	1ps
$end
$scope module clock_divider_tb $end
$var wire 1 ! clk_out $end
$var parameter 32 " DIVISOR $end
$var reg 1 # clk_in $end
$var reg 1 $ resetn $end
$scope module dut $end
$var wire 1 # clk_in $end
$var wire 1 $ resetn $end
$var parameter 32 % DIVISOR $end
$var reg 1 ! clk_out $end
$var integer 32 & counter [31:0] $end
$upscope $end
$upscope $end
$enddefinitions $end
$comment Show the parameter values. $end
$dumpall
b100 %
b100 "
$end
#0
$dumpvars
b0 &
0$
0#
x!
$end
#5000
0!
1#
#10000
0#
1$
#15000
b1 &
1#
#20000
0#
#25000
b10 &
1#
#30000
0#
#35000
b11 &
1#
#40000
0#
#45000
1!
b0 &
1#
#50000
0#
#55000
b1 &
1#
#60000
0#
#65000
b10 &
1#
#70000
0#
#75000
b11 &
1#
#80000
0#
#85000
0!
b0 &
1#
#90000
0#
#95000
b1 &
1#
#100000
0#
#105000
b10 &
1#
#110000
0#
#115000
b11 &
1#
#120000
0#
#125000
1!
b0 &
1#
#130000
0#
#135000
b1 &
1#
#140000
0#
#145000
b10 &
1#
#150000
0#
#155000
b11 &
1#
#160000
0#
#165000
0!
b0 &
1#
#170000
0#
#175000
b1 &
1#
#180000
0#
#185000
b10 &
1#
#190000
0#
#195000
b11 &
1#
#200000
0#
#205000
1!
b0 &
1#
#210000
0#
#215000
b1 &
1#
#220000
0#
#225000
b10 &
1#
#230000
0#
#235000
b11 &
1#
#240000
0#
#245000
0!
b0 &
1#
#250000
0#
#255000
b1 &
1#
#260000
0#
#265000
b10 &
1#
#270000
0#
#275000
b11 &
1#
#280000
0#
#285000
1!
b0 &
1#
#290000
0#
#295000
b1 &
1#
#300000
0#
#305000
b10 &
1#
#310000
0#
#315000
b11 &
1#
#320000
0#
#325000
0!
b0 &
1#
#330000
0#
#335000
b1 &
1#
#340000
0#
#345000
b10 &
1#
#350000
0#
#355000
b11 &
1#
#360000
0#
#365000
1!
b0 &
1#
#370000
0#
#375000
b1 &
1#
#380000
0#
#385000
b10 &
1#
#390000
0#
#395000
b11 &
1#
#400000
0#
#405000
0!
b0 &
1#
#410000
0#
#415000
b1 &
1#
#420000
0#
#425000
b10 &
1#
#430000
0#
#435000
b11 &
1#
#440000
0#
#445000
1!
b0 &
1#
#450000
0#
#455000
b1 &
1#
#460000
0#
#465000
b10 &
1#
#470000
0#
#475000
b11 &
1#
#480000
0#
#485000
0!
b0 &
1#
#490000
0#
#495000
b1 &
1#
#500000
0#
#505000
b10 &
1#
